resselt/__init__.py
resselt/registry.py
resselt/archs/__init__.py
resselt/archs/atd/__init__.py
resselt/archs/atd/arch.py
resselt/archs/compact/__init__.py
resselt/archs/compact/arch.py
resselt/archs/cugan/__init__.py
resselt/archs/cugan/arch.py
resselt/archs/dat/__init__.py
resselt/archs/dat/arch.py
resselt/archs/drct/__init__.py
resselt/archs/drct/arch.py
resselt/archs/eimn/__init__.py
resselt/archs/eimn/arch.py
resselt/archs/esrgan/__init__.py
resselt/archs/esrgan/arch.py
resselt/archs/flexnet/__init__.py
resselt/archs/flexnet/arch.py
resselt/archs/gater/__init__.py
resselt/archs/gater/arch.py
resselt/archs/gaterv2/__init__.py
resselt/archs/gaterv2/arch.py
resselt/archs/gaterv3/__init__.py
resselt/archs/gaterv3/arch.py
resselt/archs/gfisr/__init__.py
resselt/archs/gfisr/arch.py
resselt/archs/gfisrv2/__init__.py
resselt/archs/gfisrv2/arch.py
resselt/archs/lawfft/__init__.py
resselt/archs/lawfft/arch.py
resselt/archs/moesr/__init__.py
resselt/archs/moesr/arch.py
resselt/archs/mosr/__init__.py
resselt/archs/mosr/arch.py
resselt/archs/mosrv2/__init__.py
resselt/archs/mosrv2/arch.py
resselt/archs/omni/__init__.py
resselt/archs/omni/arch.py
resselt/archs/plksr/__init__.py
resselt/archs/plksr/plksr.py
resselt/archs/plksr/rplksr.py
resselt/archs/rcan/__init__.py
resselt/archs/rcan/arch.py
resselt/archs/rgt/__init__.py
resselt/archs/rgt/arch.py
resselt/archs/rha/__init__.py
resselt/archs/rha/arch.py
resselt/archs/rtmosr/__init__.py
resselt/archs/rtmosr/arch.py
resselt/archs/span/__init__.py
resselt/archs/span/arch.py
resselt/archs/spanplus/__init__.py
resselt/archs/spanplus/arch.py
resselt/archs/swinir/__init__.py
resselt/archs/swinir/arch.py
resselt/factory/__init__.py
resselt/factory/arch.py
resselt/factory/key_condition.py
resselt/utilities/__init__.py
resselt/utilities/block.py
resselt/utilities/drop_path.py
resselt/utilities/dysample.py
resselt/utilities/padding.py
resselt/utilities/state_dict.py
resselt/utilities/torch_internals.py
resselt-1.2.2.dist-info/METADATA
resselt-1.2.2.dist-info/WHEEL
resselt-1.2.2.dist-info/licenses/LICENSE.md
resselt-1.2.2.dist-info/RECORD
