Metadata-Version: 2.4
Name: resselt
Version: 1.2.2
Summary: Image Super-Resolution PyTorch architectures loader
License-File: LICENSE.md
Requires-Python: >=3.10
Requires-Dist: einops>=0.8.0
Requires-Dist: numpy>=1
Requires-Dist: safetensors<0.6
Requires-Dist: torch>=2.6.0
Provides-Extra: cu118
Requires-Dist: torch>=2.6.0; extra == 'cu118'
Provides-Extra: cu124
Requires-Dist: torch>=2.6.0; extra == 'cu124'
Provides-Extra: cu126
Requires-Dist: torch>=2.6.0; extra == 'cu126'
Provides-Extra: cu128
Requires-Dist: torch>=2.7.0; extra == 'cu128'
